{
	"projectname": "garbage-collector",
	"appid": "wxffb1550f5403e86f",
	"description": "垃圾回收小助手",
	"miniprogramRoot": "dist/",
	"cloudfunctionRoot": "cloudfunction/",
	"simulatorPluginLibVersion": {},
	"cloudfunctionTemplateRoot": "cloudfunctionTemplate",
	"compileType": "miniprogram",
	"simulatorType": "wechat",
	"libVersion": "2.7.7",
	"setting": {
		"urlCheck": true,
		"es6": true,
		"enhance": true,
		"postcss": true,
		"minified": true,
		"newFeature": true,
		"coverView": true,
		"autoAudits": false,
		"uglifyFileName": true,
		"checkInvalidKey": true,
		"checkSiteMap": true,
		"uploadWithSourceMap": true,
		"babelSetting": {
			"ignore": [],
			"disablePlugins": [],
			"outputPath": ""
		}
	},
	"condition": {}
}